devtooling/__init__.py
devtooling/main.py
devtooling/config/__init__.py
devtooling/config/detection_rules.json
devtooling/config/projects.json
devtooling/core/__init__.py
devtooling/core/detector.py
devtooling/features/__init__.py
devtooling/features/cli/__init__.py
devtooling/features/cli/arguments.py
devtooling/features/cli/handlers.py
devtooling/features/projects/__init__.py
devtooling/features/projects/manager.py
devtooling/features/projects/navigator.py
devtooling/features/tree/__init__.py
devtooling/features/tree/structure.py
devtooling/ui/__init__.py
devtooling/ui/banner.py
devtooling/ui/menu.py
devtooling/ui/styles.py
devtooling/utils/__init__.py
devtooling/utils/config.py
devtooling/utils/file_handler.py
devtooling/utils/logger.py
devtooling/utils/updater.py
devtooling_cli-0.3.0.dist-info/licenses/LICENSE
devtooling_cli-0.3.0.dist-info/METADATA
devtooling_cli-0.3.0.dist-info/WHEEL
devtooling_cli-0.3.0.dist-info/entry_points.txt
devtooling_cli-0.3.0.dist-info/top_level.txt
devtooling_cli-0.3.0.dist-info/RECORD
