Metadata-Version: 2.4
Name: devtooling-cli
Version: 0.3.0
Summary: A CLI tool for project analysis and management
Home-page: https://github.com/KloutDevs/DevTooling
Author: KloutDevs
Author-email: schmidtnahuel09@gmail.com
Project-URL: Bug Reports, https://github.com/KloutDevs/DevTooling/issues
Project-URL: Source, https://github.com/KloutDevs/DevTooling
Keywords: development,cli,project-management,utilities,project-detection,git-tools,dependency-management,code-analysis,testing-tools,documentation-generation,docker-tools,development-workflow,project-structure,automation-tools,developer-tools
Classifier: Development Status :: 4 - Beta
Classifier: Environment :: Console
Classifier: Intended Audience :: Developers
Classifier: Programming Language :: Python :: 3
Classifier: Programming Language :: Python :: 3.7
Classifier: Programming Language :: Python :: 3.8
Classifier: Programming Language :: Python :: 3.9
Classifier: Programming Language :: Python :: 3.10
Classifier: Operating System :: OS Independent
Classifier: Topic :: Software Development :: Libraries :: Python Modules
Classifier: Topic :: Utilities
Classifier: Topic :: Software Development :: Build Tools
Classifier: Topic :: Software Development :: Version Control :: Git
Classifier: Topic :: System :: Software Distribution
Classifier: Topic :: Software Development :: Testing
Classifier: Topic :: Software Development :: Documentation
Classifier: Topic :: System :: Monitoring
Classifier: Framework :: Pytest
Classifier: Intended Audience :: Information Technology
Classifier: Natural Language :: English
Requires-Python: >=3.7
License-File: LICENSE
Requires-Dist: rich>=10.0.0
Requires-Dist: questionary>=1.10.0
Requires-Dist: pyfiglet>=0.8.post1
Requires-Dist: colorama>=0.4.4
Requires-Dist: appdirs>=1.4.4
Requires-Dist: requests>=2.25.1
Dynamic: author
Dynamic: author-email
Dynamic: classifier
Dynamic: description
Dynamic: description-content-type
Dynamic: home-page
Dynamic: keywords
Dynamic: license-file
Dynamic: project-url
Dynamic: requires-dist
Dynamic: requires-python
Dynamic: summary
